gllm_misc.cpython-312-darwin.so
gllm_misc.pyi
gllm_misc/__init__.pyi
gllm_misc/cache_manager/__init__.pyi
gllm_misc/cache_manager/cache_manager.pyi
gllm_misc/chat_history_manager/__init__.pyi
gllm_misc/chat_history_manager/chat_history_manager.pyi
gllm_misc/chat_history_manager/chat_history_processor/__init__.pyi
gllm_misc/chat_history_manager/chat_history_processor/chat_history_processor.pyi
gllm_misc/chat_history_manager/chat_history_processor/lm_based_chat_history_processor.pyi
gllm_misc/chat_history_manager/chat_history_processor/similarity_based_chat_history_processor.pyi
gllm_misc/chat_history_manager/schema/__init__.pyi
gllm_misc/chat_history_manager/schema/schema.pyi
gllm_misc/context_manipulator/__init__.pyi
gllm_misc/context_manipulator/compressor/__init__.pyi
gllm_misc/context_manipulator/compressor/compressor.pyi
gllm_misc/context_manipulator/compressor/llmlingua_compressor.pyi
gllm_misc/context_manipulator/context_enricher/__init__.pyi
gllm_misc/context_manipulator/context_enricher/context_enricher.pyi
gllm_misc/context_manipulator/context_enricher/metadata_context_enricher.pyi
gllm_misc/context_manipulator/relevance_filter/__init__.pyi
gllm_misc/context_manipulator/relevance_filter/lm_based_relevance_filter.pyi
gllm_misc/context_manipulator/relevance_filter/relevance_filter.pyi
gllm_misc/context_manipulator/relevance_filter/similarity_based_relevance_filter.pyi
gllm_misc/context_manipulator/repacker/__init__.pyi
gllm_misc/context_manipulator/repacker/_strategy.pyi
gllm_misc/context_manipulator/repacker/repacker.pyi
gllm_misc/graph_transformer/__init__.pyi
gllm_misc/graph_transformer/constant.pyi
gllm_misc/graph_transformer/lm_based_graph_transformer.pyi
gllm_misc/graph_transformer/lm_based_mindmap_transformer.pyi
gllm_misc/graph_transformer/prompt.pyi
gllm_misc/graph_transformer/schema.pyi
gllm_misc/graph_transformer/utils.pyi
gllm_misc/localization_manager/__init__.pyi
gllm_misc/localization_manager/lang_detector/__init__.pyi
gllm_misc_binary-0.8.8.dist-info/METADATA
gllm_misc_binary-0.8.8.dist-info/WHEEL
gllm_misc_binary-0.8.8.dist-info/top_level.txt
gllm_misc_binary-0.8.8.dist-info/RECORD
