Metadata-Version: 2.2
Name: gllm-misc-binary
Version: 0.8.8
Summary: A library containing miscellaneous components for Gen AI applications.
Author-email: Dimitrij Ray <dimitrij.ray@gdplabs.id>, Henry Wicaksono <henry.wicaksono@gdplabs.id>, Resti Febriana <resti.febriana@gdplabs.id>, Kadek Denaya <kadek.d.r.diana@gdplabs.id>
Requires-Python: <3.13,>=3.11
Requires-Dist: poetry<3.0.0,>=2.1.3
Requires-Dist: gllm-core-binary<0.4.0,>=0.3.0
Requires-Dist: gllm-inference-binary[google]<0.6.0,>=0.5.0
Requires-Dist: gllm-datastore-binary[chroma]<0.6.0,>=0.5.0
Requires-Dist: azure-search-documents<12.0.0,>=11.5.1
Requires-Dist: langchain<0.4.0,>=0.3.0
Requires-Dist: pycountry<25.0.0,>=24.6.1
Requires-Dist: python-magic<0.5.0,>=0.4.27; sys_platform != "win32"
Requires-Dist: python-magic-bin<0.5.0,>=0.4.14; sys_platform == "win32"
Requires-Dist: semantic-router<0.2.0,>=0.1.0
Requires-Dist: transformers<5.0.0,>=4.52.4
Provides-Extra: dev
Requires-Dist: coverage<8.0.0,>=7.4.4; extra == "dev"
Requires-Dist: mypy<2.0.0,>=1.15.0; extra == "dev"
Requires-Dist: pre-commit<4.0.0,>=3.7.0; extra == "dev"
Requires-Dist: pytest<9.0.0,>=8.1.1; extra == "dev"
Requires-Dist: pytest-asyncio<0.24.0,>=0.23.6; extra == "dev"
Requires-Dist: pytest-cov<6.0.0,>=5.0.0; extra == "dev"
Requires-Dist: ruff<0.7.0,>=0.6.7; extra == "dev"
Provides-Extra: audio
Requires-Dist: google-cloud-speech<3.0.0,>=2.28.0; extra == "audio"
Requires-Dist: google-cloud-storage<3.0.0,>=2.18.2; extra == "audio"
Requires-Dist: langcodes<4.0.0,>=3.4.1; extra == "audio"
Requires-Dist: openai<2.0.0,>=1.98.0; extra == "audio"
Requires-Dist: soundfile<0.14.0,>=0.13.1; extra == "audio"
Requires-Dist: youtube-transcript-api<2.0.0,>=1.1.0; extra == "audio"
Requires-Dist: yt-dlp>=2025.6.9; extra == "audio"
Provides-Extra: google-translate
Requires-Dist: googletrans<5.0.0,>=4.0.2; extra == "google-translate"
Provides-Extra: image
Requires-Dist: boto3<2.0.0,>=1.38.10; extra == "image"
Requires-Dist: pillow<12.0.0,>=11.2.1; extra == "image"
Requires-Dist: aioresponses<0.8.0,>=0.7.0; extra == "image"
Provides-Extra: json-repair
Requires-Dist: json-repair<0.48.0,>=0.47.6; extra == "json-repair"
Provides-Extra: langdetect
Requires-Dist: langdetect<2.0.0,>=1.0.9; extra == "langdetect"
Provides-Extra: language
Provides-Extra: llmlingua
Requires-Dist: llmlingua<0.3.0,>=0.2.2; extra == "llmlingua"
Requires-Dist: torch==2.2.2; (sys_platform == "darwin" and platform_machine == "x86_64") and extra == "llmlingua"
Requires-Dist: torch<3.0.0,>=2.2.2; (sys_platform == "darwin" and platform_machine == "arm64") and extra == "llmlingua"
Requires-Dist: torch<3.0.0,>=2.2.2; sys_platform != "darwin" and extra == "llmlingua"
Provides-Extra: kg
